Workbook

Sheet Portfolio
A1: id | B1: name | C1: sector | D1: status | E1: vintage | F1: invested | G1: entryRev | H1: entryEbitda | I1: entryGM | J1: entryDebt | K1: entryMult | L1: curRev | M1: curEbitda | N1: curGM | O1: curDebt | P1: curMult | Q1: hcEntry | R1: hcCur | S1: nrr | T1: cacPayback | U1: notes
A2: hc1 | B2: Meridian Dental Group | C2: Healthcare Services | D2: Outperforming | E2: 2022-03-15 | F2: 85 | G2: 120 | H2: 18 | I2: 0.7 | J2: 77 | K2: 9 | L2: 165 | M2: 30 | N2: 0.7 | O2: 52 | P2: 11 | Q2: 1100 | R2: 1450 | U2: DSO roll-up; 14 bolt-ons during hold
A3: hc2 | B3: Cascade Behavioral Health | C3: Healthcare Services | D3: Outperforming | E3: 2021-09-01 | F3: 62 | G3: 90 | H3: 11 | I3: 0.55 | J3: 31.5 | K3: 8.5 | L3: 135 | M3: 19 | N3: 0.58 | O3: 20 | P3: 10 | Q3: 650 | R3: 990 | U3: In-network with major payors; 4→18 states
A4: hc3 | B4: AltaCare Home Health | C4: Healthcare Services | D4: On plan | E4: 2020-11-10 | F4: 40 | G4: 55 | H4: 7 | I4: 0.42 | J4: 16 | K4: 8 | L4: 72 | M4: 9.5 | N4: 0.43 | O4: 11 | P4: 8.5 | Q4: 380 | R4: 510 | U4: Route density improved 22%
A5: cb1 | B5: Northwind Coffee Co. | C5: Consumer Brands | D5: Outperforming | E5: 2019-04-08 | F5: 55 | G5: 130 | H5: 14 | I5: 0.38 | J5: 57 | K5: 8 | L5: 185 | M5: 24 | N5: 0.42 | O5: 40 | P5: 10 | Q5: 920 | R5: 1180 | U5: DTC channel scaled 8% → 27% of revenue
A6: cb2 | B6: Verdant Pet Foods | C6: Consumer Brands | D6: Outperforming | E6: 2022-08-12 | F6: 48 | G6: 75 | H6: 9 | I6: 0.34 | J6: 33 | K6: 9 | L6: 105 | M6: 14 | N6: 0.36 | O6: 26 | P6: 11 | Q6: 310 | R6: 415 | U6: Premium pet trend; 2 SKU lines launched
A7: cb3 | B7: Lumen Apparel | C7: Consumer Brands | D7: Underperforming | E7: 2021-02-22 | F7: 70 | G7: 160 | H7: 19 | I7: 0.44 | J7: 72.5 | K7: 7.5 | L7: 145 | M7: 14 | N7: 0.41 | O7: 50 | P7: 6.5 | Q7: 1450 | R7: 1180 | U7: Wholesale channel pressure; ops reset Q2 2026
A8: sw1 | B8: Polaris HRTech | C8: B2B Software | D8: Outperforming | E8: 2021-11-18 | F8: 96 | G8: 18 | H8: 3 | I8: 0.74 | J8: 0 | K8: 32 | L8: 42 | M8: 9 | N8: 0.78 | O8: 0 | P8: 28 | Q8: 160 | R8: 280 | S8: 118 | T8: 18 | U8: NRR 118%; expanding Canada/UK
A9: sw2 | B9: Cipher Compliance Software | C9: B2B Software | D9: On plan | E9: 2022-05-04 | F9: 60 | G9: 12 | H9: 2 | I9: 0.76 | J9: 0 | K9: 30 | L9: 22 | M9: 5 | N9: 0.79 | O9: 0 | P9: 28 | Q9: 95 | R9: 160 | S9: 112 | T9: 22 | U9: SEC cyber-disclosure tailwind
A10: sw3 | B10: Atlas Field Service Cloud | C10: B2B Software | D10: Outperforming | E10: 2020-10-09 | F10: 70 | G10: 18 | H10: 2.5 | I10: 0.72 | J10: 0 | K10: 28 | L10: 48 | M10: 12 | N10: 0.79 | O10: 0 | P10: 26 | Q10: 140 | R10: 280 | S10: 121 | T10: 14 | U10: Best NRR; potential strategic exit
A11: in1 | B11: Summit Steel Distribution | C11: Industrial Services | D11: Outperforming | E11: 2021-07-02 | F11: 72 | G11: 210 | H11: 20 | I11: 0.16 | J11: 68 | K11: 7 | L11: 290 | M11: 36 | N11: 0.18 | O11: 50 | P11: 8 | Q11: 520 | R11: 640 | U11: Two bolt-ons; logistics network optimization
A12: fs1 | B12: Sterling Specialty Insurance | C12: Financial Services | D12: Outperforming | E12: 2021-05-17 | F12: 90 | G12: 75 | H12: 10.5 | I12: 0.62 | J12: 25.5 | K12: 11 | L12: 118 | M12: 20 | N12: 0.65 | O12: 18 | P12: 13 | Q12: 240 | R12: 330 | U12: Hard market; loss ratio improved 480bps
A13: fs2 | B13: Quill Wealth Advisors | C13: Financial Services | D13: Outperforming | E13: 2019-11-14 | F13: 80 | G13: 62 | H13: 10 | I13: 0.68 | J13: 20 | K13: 10 | L13: 108 | M13: 22 | N13: 0.71 | O13: 15 | P13: 12 | Q13: 165 | R13: 240 | U13: RIA roll-up; 11 advisor practices added

Sheet Single Portco Starter
A1: id | B1: name | C1: sector | D1: status | E1: vintage | F1: invested | G1: entryRev | H1: entryEbitda | I1: entryGM | J1: entryDebt | K1: entryMult | L1: curRev | M1: curEbitda | N1: curGM | O1: curDebt | P1: curMult | Q1: hcEntry | R1: hcCur | S1: nrr | T1: cacPayback | U1: notes
A2: solo1 | B2: Atlas Field Service Cloud | C2: B2B Software | D2: Outperforming | E2: 2020-10-09 | F2: 70 | G2: 18 | H2: 2.5 | I2: 0.72 | J2: 0 | K2: 28 | L2: 48 | M2: 12 | N2: 0.79 | O2: 0 | P2: 26 | Q2: 140 | R2: 280 | S2: 121 | T2: 14 | U2: Single-portco demo — drop into the dashboard to see KPI #1.1.1 read '1 portfolio company'

Sheet Summary
A1: North Castle Partners — Fund III Portfolio Summary
A2: Live formulas — change Portfolio sheet, this updates automatically
A4: 1. Fund-level KPIs
A5: Portfolio companies | B5: =COUNTA(Portfolio!B2:B13) -> 12
A6: Total invested ($M) | B6: =SUM(Portfolio!F2:F13) -> 828
A7: Total current revenue ($M) | B7: =SUM(Portfolio!L2:L13) -> 1435
A8: Total current EBITDA ($M) | B8: =SUM(Portfolio!M2:M13) -> 214.5
A9: Weighted EBITDA margin | B9: =SUM(Portfolio!M2:M13)/SUM(Portfolio!L2:L13) -> 0.14947735
A10: Aggregate fair value ($M) | B10: =SUMPRODUCT(Portfolio!M2:M13,Portfolio!P2:P13)-SUM(Portfolio!O2:O13) -> 2319.75
A11: Gross MOIC | B11: =(SUMPRODUCT(Portfolio!M2:M13,Portfolio!P2:P13)-SUM(Portfolio!O2:O13))/SUM(Portfolio!F2:F13) -> 2.8016304
A12: EBITDA growth ($M, abs) | B12: =SUM(Portfolio!M2:M13)-SUM(Portfolio!H2:H13) -> 88.5
A13: EBITDA growth (%) | B13: =SUM(Portfolio!M2:M13)/SUM(Portfolio!H2:H13)-1 -> 0.70238095
A14: Total headcount (current) | B14: =SUM(Portfolio!R2:R13) -> 7655
A15: Net headcount added | B15: =SUM(Portfolio!R2:R13)-SUM(Portfolio!Q2:Q13) -> 1525
A17: 2. Per-portco quick math (current snapshot)
A18: Company | B18: MOIC | C18: EBITDA margin | D18: EBITDA growth
A19: =Portfolio!B2 -> Meridian Dental Group | B19: =(Portfolio!M2*Portfolio!P2-Portfolio!O2)/Portfolio!F2 -> 3.2705882 | C19: =Portfolio!M2/Portfolio!L2 -> 0.18181818 | D19: =Portfolio!M2/Portfolio!H2-1 -> 0.66666667
A20: =Portfolio!B3 -> Cascade Behavioral Health | B20: =(Portfolio!M3*Portfolio!P3-Portfolio!O3)/Portfolio!F3 -> 2.7419355 | C20: =Portfolio!M3/Portfolio!L3 -> 0.14074074 | D20: =Portfolio!M3/Portfolio!H3-1 -> 0.72727273
A21: =Portfolio!B4 -> AltaCare Home Health | B21: =(Portfolio!M4*Portfolio!P4-Portfolio!O4)/Portfolio!F4 -> 1.74375 | C21: =Portfolio!M4/Portfolio!L4 -> 0.13194444 | D21: =Portfolio!M4/Portfolio!H4-1 -> 0.35714286
A22: =Portfolio!B5 -> Northwind Coffee Co. | B22: =(Portfolio!M5*Portfolio!P5-Portfolio!O5)/Portfolio!F5 -> 3.6363636 | C22: =Portfolio!M5/Portfolio!L5 -> 0.12972973 | D22: =Portfolio!M5/Portfolio!H5-1 -> 0.71428571
A23: =Portfolio!B6 -> Verdant Pet Foods | B23: =(Portfolio!M6*Portfolio!P6-Portfolio!O6)/Portfolio!F6 -> 2.6666667 | C23: =Portfolio!M6/Portfolio!L6 -> 0.13333333 | D23: =Portfolio!M6/Portfolio!H6-1 -> 0.55555556
A24: =Portfolio!B7 -> Lumen Apparel | B24: =(Portfolio!M7*Portfolio!P7-Portfolio!O7)/Portfolio!F7 -> 0.58571429 | C24: =Portfolio!M7/Portfolio!L7 -> 0.096551724 | D24: =Portfolio!M7/Portfolio!H7-1 -> -0.26315789
A25: =Portfolio!B8 -> Polaris HRTech | B25: =(Portfolio!M8*Portfolio!P8-Portfolio!O8)/Portfolio!F8 -> 2.625 | C25: =Portfolio!M8/Portfolio!L8 -> 0.21428571 | D25: =Portfolio!M8/Portfolio!H8-1 -> 2
A26: =Portfolio!B9 -> Cipher Compliance Software | B26: =(Portfolio!M9*Portfolio!P9-Portfolio!O9)/Portfolio!F9 -> 2.3333333 | C26: =Portfolio!M9/Portfolio!L9 -> 0.22727273 | D26: =Portfolio!M9/Portfolio!H9-1 -> 1.5
A27: =Portfolio!B10 -> Atlas Field Service Cloud | B27: =(Portfolio!M10*Portfolio!P10-Portfolio!O10)/Portfolio!F10 -> 4.4571429 | C27: =Portfolio!M10/Portfolio!L10 -> 0.25 | D27: =Portfolio!M10/Portfolio!H10-1 -> 3.8
A28: =Portfolio!B11 -> Summit Steel Distribution | B28: =(Portfolio!M11*Portfolio!P11-Portfolio!O11)/Portfolio!F11 -> 3.3055556 | C28: =Portfolio!M11/Portfolio!L11 -> 0.12413793 | D28: =Portfolio!M11/Portfolio!H11-1 -> 0.8
A29: =Portfolio!B12 -> Sterling Specialty Insurance | B29: =(Portfolio!M12*Portfolio!P12-Portfolio!O12)/Portfolio!F12 -> 2.6888889 | C29: =Portfolio!M12/Portfolio!L12 -> 0.16949153 | D29: =Portfolio!M12/Portfolio!H12-1 -> 0.9047619
A30: =Portfolio!B13 -> Quill Wealth Advisors | B30: =(Portfolio!M13*Portfolio!P13-Portfolio!O13)/Portfolio!F13 -> 3.1125 | C30: =Portfolio!M13/Portfolio!L13 -> 0.2037037 | D30: =Portfolio!M13/Portfolio!H13-1 -> 1.2

Sheet Field Reference
A1: Column | B1: Type | C1: Notes
A2: id | B2: text | C2: Unique key. Re-using an id REPLACES that portco on import.
A3: name | B3: text | C3: Required. Match exactly across uploads to update an existing row.
A4: sector | B4: enum | C4: Healthcare Services / Consumer Brands / B2B Software / Industrial Services / Financial Services
A5: status | B5: enum | C5: Outperforming / On plan / Underperforming / Distressed
A6: vintage | B6: YYYY-MM-DD | C6: Acquisition date — drives the 'hold years' calculation
A7: invested | B7: $M | C7: Equity check at close (cumulative if follow-ons)
A8: entryRev | B8: $M | C8: Trailing-twelve revenue at close
A9: entryEbitda | B9: $M | C9: Same period as entryRev
A10: entryGM | B10: decimal | C10: 0.55 = 55%
A11: entryDebt | B11: $M | C11: Net debt at entry
A12: entryMult | B12: x | C12: EV/EBITDA at close
... A22: notes | B22: text | C22: Free-form commentary surfaced in the per-portco modal
A24: DERIVED IN DASHBOARD — DO NOT ENTER:
A25: MOIC | C25: (curEbitda × curMult − curDebt) / invested
A26: IRR (approx) | C26: MOIC^(1/holdYears) − 1
A27: Revenue / EBITDA CAGR | C27: (cur / entry)^(1/holdYears) − 1
A28: Value bridge | C28: (ΔEBITDA × entryMult) + (Δmult × curEbitda) + (entryDebt − curDebt)
A29: Marginal benefit | C29: curEbitda − entryEbitda × (1 + sector organic CAGR)^holdYears
